<?xml version="1.0" encoding="UTF-8"?>
<!DOCTYPE tiles-definitions PUBLIC
       "-//Apache Software Foundation//DTD Tiles Configuration 2.1//EN"
       "http://tiles.apache.org/dtds/tiles-config_2_1.dtd">

<tiles-definitions>

    <definition extends="defaultTemplate" name="developer/client/list">
        <put-attribute name="primaryTitle" value="已註冊應用服務列表"/>
        <put-attribute name="secondaryTitle" value="下列是您已註冊使用NCU API的應用服務"/>
        <put-attribute name="mainContent" value="/WEB-INF/views/developer/client/list.jsp" />
    </definition>    

	<definition extends="defaultTemplate" name="developer/client/edit">
        <put-attribute name="primaryTitle" value="修改應用服務"/>
        <put-attribute name="secondaryTitle" value="修改內容"/>
		<put-attribute name="mainContent" value="/WEB-INF/views/developer/client/edit.jsp" />
	</definition>

    <definition extends="defaultTemplate" name="developer/client/register">
        <put-attribute name="primaryTitle" value="註冊應用服務"/>
        <put-attribute name="secondaryTitle" value="註冊後將可使用NCU API"/>
        <put-attribute name="mainContent" value="/WEB-INF/views/developer/client/register.jsp" />
    </definition>
    
</tiles-definitions>
